shinka/__init__.py
shinka/batch.py
shinka/cli.py
shinka/core.py
shinka/py.typed
shinka-0.3.0.dist-info/WHEEL
shinka-0.3.0.dist-info/entry_points.txt
shinka-0.3.0.dist-info/METADATA
shinka-0.3.0.dist-info/RECORD
