Metadata-Version: 2.3
Name: shinka
Version: 0.3.0
Summary: A high-quality image upscaling package using a genetically-evolved algorithm.
Author: jordan legg
Author-email: jordan legg <me@404missing.link>
License: MIT License
Classifier: License :: OSI Approved :: MIT License
Classifier: Programming Language :: Python :: 3
Classifier: Programming Language :: Python :: 3.8
Classifier: Programming Language :: Python :: 3.9
Classifier: Programming Language :: Python :: 3.10
Classifier: Programming Language :: Python :: 3.11
Classifier: Programming Language :: Python :: 3.12
Classifier: Operating System :: OS Independent
Classifier: Intended Audience :: Developers
Classifier: Topic :: Multimedia :: Graphics :: Graphics Conversion
Classifier: Topic :: Software Development :: Libraries :: Python Modules
Requires-Dist: numpy
Requires-Dist: pillow
Requires-Dist: scipy
Requires-Dist: typer[all] ; extra == 'cli'
Requires-Dist: rich ; extra == 'cli'
Requires-Python: >=3.8
Provides-Extra: cli
